xml_api/__init__.py
xml_api/cli.py
xml_api/core/__init__.py
xml_api/core/client/__init__.py
xml_api/core/client/client.py
xml_api/core/client/http.py
xml_api/core/client/res_data.py
xml_api/core/client/sql.py
xml_api/core/client/tcp.py
xml_api/core/executor/__init__.py
xml_api/core/executor/executor.py
xml_api/core/process/__init__.py
xml_api/core/process/post.py
xml_api/core/process/pre.py
xml_api/core/process/processor.py
xml_api/exception/__init__.py
xml_api/exception/client.py
xml_api/exception/db.py
xml_api/exception/expect.py
xml_api/exception/inf_process.py
xml_api/exception/my_assertion_error.py
xml_api/exception/my_exception.py
xml_api/exception/other.py
xml_api/exception/post.py
xml_api/exception/pre.py
xml_api/function/__init__.py
xml_api/function/analysis/__init__.py
xml_api/function/analysis/xml_parser.py
xml_api/function/beautify/__init__.py
xml_api/function/beautify/beautify.py
xml_api/function/beautify/beautify_json.py
xml_api/function/beautify/beautify_xml.py
xml_api/function/cfg/__init__.py
xml_api/function/cfg/cfg.py
xml_api/function/cfg/config.py
xml_api/function/cfg/my_configparser.py
xml_api/function/cookies/__init__.py
xml_api/function/cookies/cookie.py
xml_api/function/data/__init__.py
xml_api/function/data/inf.py
xml_api/function/data/interface.py
xml_api/function/database/__init__.py
xml_api/function/database/db.py
xml_api/function/env/__init__.py
xml_api/function/env/environment.py
xml_api/function/express/__init__.py
xml_api/function/express/express.py
xml_api/function/express/module.py
xml_api/function/format/__init__.py
xml_api/function/format/color.py
xml_api/function/format/format.py
xml_api/function/func/__init__.py
xml_api/function/func/_inner.py
xml_api/function/jvm/__init__.py
xml_api/function/jvm/jvm.py
xml_api/function/jvm/jvm_process.py
xml_api/function/parse/__init__.py
xml_api/function/parse/files_parse.py
xml_api/function/parse/json_parse.py
xml_api/function/parse/key/__init__.py
xml_api/function/parse/key/point.py
xml_api-0.0.6.dist-info/entry_points.txt
xml_api-0.0.6.dist-info/LICENSE
xml_api-0.0.6.dist-info/METADATA
xml_api-0.0.6.dist-info/WHEEL
xml_api-0.0.6.dist-info/RECORD
